playgroundutils/__init__.py
playgroundutils/app.py
playgroundutils/components.py
playgroundutils/llm_api_helpers.py
playgroundutils/streaming.py
playgroundutils/user.py
playgroundutils/media/Favicon.png
playgroundutils/media/__init__.py
playgroundutils/media/logo.png
playgroundutils-0.1.1.dist-info/LICENSE
playgroundutils-0.1.1.dist-info/METADATA
playgroundutils-0.1.1.dist-info/NOTICE
playgroundutils-0.1.1.dist-info/WHEEL
playgroundutils-0.1.1.dist-info/top_level.txt
playgroundutils-0.1.1.dist-info/RECORD
