Metadata-Version: 2.1
Name: playgroundutils
Version: 0.1.1
Summary: Helper functions for the ConfidentialMind stack, primarily for Streamlit apps
Author-email: confidentialmind <info@confidentialmind.com>
License: Apache-2.0
Project-URL: Homepage, https://www.confidentialmind.com/
Requires-Python: >=3.10
License-File: LICENSE
License-File: NOTICE
Requires-Dist: pydantic >=2.2
Requires-Dist: websockets >=12.0
Requires-Dist: requests >=2.32.2
Requires-Dist: Pillow >=9.5.0
Requires-Dist: streamlit >=1.26.0
Requires-Dist: sseclient-py >=1.8.0
Requires-Dist: pyjwt >=2.8.0
